Workbook

Sheet Resumen
A1: Plataforma de Eventos Online — Plan de Trabajo y Backlog
A3: Metodología
A4: Marco de trabajo | B4: Scrum
A5: Duración de Sprint | B5: 2 semanas
A6: Duración total estimada | B6: 26 semanas (~6 meses)
A7: Número de Sprints | B7: 13 (Sprint 0 de fundación + Sprints 1 a 12)
A9: Fecha de inicio del proyecto | B9: 2026-09-01
A11: Equipo del proyecto
A12: Rol | B12: Cantidad
A13: Líder Técnico (LT) | B13: 1
A14: Product Owner | B14: 1
A15: Scrum Master | B15: 1
A16: Backend Developer | B16: 2
A17: Frontend Developer | B17: 2
A18: FullStack Developer | B18: 1
A19: QA Engineer | B19: 2
A20: UX Designer | B20: 1
A21: UI Designer | B21: 1
A22: Total equipo | B22: =SUM(B13:B21) -> 12
A24: Áreas de soporte TI (fuera del equipo Scrum)
A25: • Arquitectura
A26: • Base de Datos (DBA)
A27: • Seguridad
A28: • Plataforma / Infraestructura
A30: Entornos
A31: DEV → QA → Staging → Production

Sheet Roadmap
A1: Sprint | B1: Semanas | C1: Fecha Inicio | D1: Fecha Fin | E1: Objetivo del Sprint | F1: Entregable Clave | G1: Épicas | H1: Dependencia de Soporte TI | I1: Entorno objetivo
A2: Sprint 0 | B2: 1-2 | C2: =Resumen!$B$9+(1-1)*7 -> 46266 | D2: =C2+13 -> 46279 | E2: Fundación técnica: repos, CI/CD, IaC (Terraform) baseline, aprobación de arquitectura, entornos DEV/QA provisionados, design system y wireframes iniciales. | F2: Entornos DEV/QA activos + pipeline CI/CD funcionando | G2: E1 | H2: Arquitectura, Plataforma, Seguridad | I2: DEV
A3: Sprint 1 | B3: 3-4 | C3: =Resumen!$B$9+(3-1)*7 -> 46280 | D3: =C3+13 -> 46293 | E3: Autenticación y autorización (OIDC/JWT), scaffold del frontend con login. | F3: IdentityService + login funcional | G3: E2, E10 | H3: Seguridad | I3: DEV
A4: Sprint 2 | B4: 5-6 | C4: =Resumen!$B$9+(5-1)*7 -> 46294 | D4: =C4+13 -> 46307 | E4: Catálogo de eventos: CRUD de eventos y zonas, modelo de datos, migraciones. | F4: EventService CRUD + listado en frontend | G4: E3, E10 | H4: Base de Datos | I4: DEV
A5: Sprint 3 | B5: 7-8 | C5: =Resumen!$B$9+(7-1)*7 -> 46308 | D5: =C5+13 -> 46321 | E5: Publicación de eventos y mensajería (EventCreated); búsqueda base con indexación. | F5: Publicación de eventos + búsqueda simple | G5: E3, E4, E10 | H5: Arquitectura | I5: DEV → QA
A6: Sprint 4 | B6: 9-10 | C6: =Resumen!$B$9+(9-1)*7 -> 46322 | D6: =C6+13 -> 46335 | E6: Búsqueda avanzada (facetas/ranking); modelo de inventario de zonas; backoffice de eventos. | F6: Búsqueda avanzada + backoffice CRUD | G6: E4, E5, E11 | H6: Base de Datos | I6: QA
A7: Sprint 5 | B7: 11-12 | C7: =Resumen!$B$9+(11-1)*7 -> 46336 | D7: =C7+13 -> 46349 | E7: Holds de inventario con Redis y control de concurrencia; carrito/selección de zonas en frontend. | F7: Reserva temporal de zonas sin sobreventa | G7: E5, E10 | H7: Plataforma | I7: QA
A8: Sprint 6 | B8: 13-14 | C8: =Resumen!$B$9+(13-1)*7 -> 46350 | D8: =C8+13 -> 46363 | E8: Orquestación de compra (Saga) e integración con PSP en sandbox; checkout en frontend. | F8: Flujo de compra end-to-end (sandbox) | G8: E6, E10 | H8: Seguridad, Arquitectura | I8: QA → Staging
A9: Sprint 7 | B9: 15-16 | C9: =Resumen!$B$9+(15-1)*7 -> 46364 | D9: =C9+13 -> 46377 | E9: Compensaciones de la Saga (reembolsos, liberación de stock); pruebas de flujo completo. | F9: Saga de compra resiliente a fallos de pago | G9: E6 | H9: Arquitectura | I9: Staging
A10: Sprint 8 | B10: 17-18 | C10: =Resumen!$B$9+(17-1)*7 -> 46378 | D10: =C10+13 -> 46391 | E10: Emisión de tickets (QR/Barcode) con almacenamiento en S3; notificaciones multicanal. | F10: Ticket digital emitido y enviado por correo | G10: E7, E9 | H10: Plataforma | I10: Staging
A11: Sprint 9 | B11: 19-20 | C11: =Resumen!$B$9+(19-1)*7 -> 46392 | D11: =C11+13 -> 46405 | E11: Validación de ingreso (Check-in) con soporte de modo offline; vista de staff de puerta. | F11: Check-in funcional online y offline | G11: E8, E11 | H11: Plataforma | I11: Staging
A12: Sprint 10 | B12: 21-22 | C12: =Resumen!$B$9+(21-1)*7 -> 46406 | D12: =C12+13 -> 46419 | E12: Observabilidad (logs centralizados, tracing, dashboards) y hardening de seguridad. | F12: Tablero de monitoreo + hallazgos de seguridad cerrados | G12: E12 | H12: Seguridad, Plataforma | I12: Staging
A13: Sprint 11 | B13: 23-24 | C13: =Resumen!$B$9+(23-1)*7 -> 46420 | D13: =C13+13 -> 46433 | E13: Pruebas de carga simulando picos de venta (sala de espera virtual); UAT con stakeholders. | F13: Reporte de performance + UAT aprobado | G13: E13 | H13: Plataforma, Arquitectura | I13: Staging
A14: Sprint 12 | B14: 25-26 | C14: =Resumen!$B$9+(25-1)*7 -> 46434 | D14: =C14+13 -> 46447 | E14: Despliegue a producción, documentación final, capacitación a soporte, go-live. | F14: Sistema en producción (v1) | G14: E13 | H14: Arquitectura, Plataforma, Seguridad, Base de Datos | I14: Production

Sheet Backlog
A1: ID | B1: Épica | C1: Historia de Usuario | D1: Prioridad | E1: Story Points | F1: Rol Principal | G1: Sprint | H1: Dependencia de Soporte TI
A2: BL-001 | B2: E1 - Fundación técnica | C2: Como equipo, necesitamos repositorios, ramas y convenciones de código definidas para empezar a desarrollar de forma ordenada. | D2: Alta | E2: 3 | F2: LT | G2: Sprint 0 | H2: Arquitectura
A3: BL-002 | B3: E1 - Fundación técnica | C3: Como equipo, necesitamos un pipeline CI/CD básico (build + test) para cada API antes de escribir la primera línea de negocio. | D3: Alta | E3: 5 | F3: Backend | G3: Sprint 0 | H3: Plataforma
A4: BL-003 | B4: E1 - Fundación técnica | C4: Como equipo, necesitamos los entornos DEV y QA aprovisionados en AWS (o on-prem) para poder desplegar. | D4: Alta | E4: 8 | F4: LT | G4: Sprint 0 | H4: Plataforma
A5: BL-004 | B5: E1 - Fundación técnica | C5: Como Admin, necesito que el diagrama de arquitectura esté aprobado por el área de Arquitectura antes de iniciar desarrollo de dominio. | D5: Alta | E5: 3 | F5: LT | G5: Sprint 0 | H5: Arquitectura
A6: BL-005 | B6: E1 - Fundación técnica | C6: Como UX/UI, necesito wireframes iniciales del flujo de compra y del backoffice para guiar el desarrollo frontend. | D6: Media | E6: 5 | F6: UX | G6: Sprint 0 | H6: Ninguna
A7: BL-006 | B7: E2 - Identidad y Accesos | C7: Como usuario, quiero autenticarme con usuario/contraseña y recibir un JWT para poder acceder a la plataforma. | D7: Alta | E7: 8 | F7: Backend | G7: Sprint 1 | H7: Seguridad
A8: BL-007 | B8: E2 - Identidad y Accesos | C8: Como Admin, quiero que los endpoints de escritura validen mi rol para evitar accesos no autorizados. | D8: Alta | E8: 5 | F8: Backend | G8: Sprint 1 | H8: Seguridad
A9: BL-008 | B9: E2 - Identidad y Accesos | C9: Como Cliente, quiero ver una pantalla de login funcional en el frontend para iniciar sesión. | D9: Alta | E9: 5 | F9: Frontend | G9: Sprint 1 | H9: Ninguna
A10: BL-009 | B10: E3 - Catálogo de Eventos | C10: Como Organizador, quiero crear un evento con múltiples zonas, precios y capacidad en una sola operación. | D10: Alta | E10: 8 | F10: Backend | G10: Sprint 2 | H10: Base de Datos
A11: BL-010 | B11: E3 - Catálogo de Eventos | C11: Como Cliente, quiero listar los eventos publicados para poder explorarlos. | D11: Alta | E11: 5 | F11: Backend | G11: Sprint 2 | H11: Ninguna
A12: BL-011 | B12: E3 - Catálogo de Eventos | C12: Como Organizador, quiero ver el detalle de un evento con sus zonas y disponibilidad. | D12: Media | E12: 3 | F12: Backend | G12: Sprint 2 | H12: Ninguna
A13: BL-012 | B13: E3 - Catálogo de Eventos | C13: Como Cliente, quiero ver el listado de eventos en una pantalla web atractiva y responsiva. | D13: Alta | E13: 8 | F13: Frontend | G13: Sprint 2 | H13: Ninguna
... A45: BL-044 | B45: E13 - QA, Performance y Lanzamiento | C45: Como equipo de soporte, quiero documentación funcional y técnica completa para poder operar el sistema tras el lanzamiento. | D45: Alta | E45: 8 | F45: LT | G45: Sprint 12 | H45: Ninguna
C47: Total Story Points | E47: =SUM(E2:E45) -> 282
C48: Historias de Alta prioridad | E48: =COUNTIF(D2:D45,"Alta") -> 34
